{
  "$schema": "https://developer.microsoft.com/json-schemas/spfx-build/package-solution.schema.json",
  "solution": {
    "name": "playwright-test-client-side-solution",
    "id": "47f6ae39-5f23-4cca-a4b5-63e7069e8438",
    "version": "1.0.0.0",
    "includeClientSideAssets": true,
    "skipFeatureDeployment": true,
    "isDomainIsolated": false,
    "developer": {
      "name": "",
      "websiteUrl": "",
      "privacyUrl": "",
      "termsOfUseUrl": "",
      "mpnId": "Undefined-1.20.0"
    },
    "metadata": {
      "shortDescription": {
        "default": "playwright-test description"
      },
      "longDescription": {
        "default": "playwright-test description"
      },
      "screenshotPaths": [],
      "videoUrl": "",
      "categories": []
    },
    "features": [
      {
        "title": "playwright-test Feature",
        "description": "The feature that activates elements of the playwright-test solution.",
        "id": "1d3f8b62-2f09-49c0-b8e7-77ef6475b53f",
        "version": "1.0.0.0"
      }
    ]
  },
  "paths": {
    "zippedPackage": "solution/playwright-test.sppkg"
  }
}
